app/__init__.py
app/client.py
app/config.py
app/main.py
app/resources/__init__.py
app/resources/server_info.py
app/tools/__init__.py
app/tools/cancel_video.py
app/tools/create_video.py
app/tools/get_video.py
app/tools/list_videos.py
volcengine_video_mcp-0.1.1.dist-info/METADATA
volcengine_video_mcp-0.1.1.dist-info/WHEEL
volcengine_video_mcp-0.1.1.dist-info/entry_points.txt
volcengine_video_mcp-0.1.1.dist-info/licenses/LICENSE
volcengine_video_mcp-0.1.1.dist-info/RECORD
