Metadata-Version: 2.4
Name: volcengine-video-mcp
Version: 0.1.1
Summary: MCP server for Volcengine (Doubao) Video Generation API
Author-email: Lupin <lupin@example.com>
License: MIT
License-File: LICENSE
Keywords: ai,doubao,fastmcp,mcp,video-generation,volcengine
Classifier: Development Status :: 4 - Beta
Classifier: Intended Audience :: Developers
Classifier: License :: OSI Approved :: MIT License
Classifier: Programming Language :: Python :: 3
Classifier: Programming Language :: Python :: 3.11
Classifier: Programming Language :: Python :: 3.12
Classifier: Programming Language :: Python :: 3.13
Classifier: Topic :: Software Development :: Libraries :: Python Modules
Requires-Python: >=3.11
Requires-Dist: fastmcp==2.13.0.1
Requires-Dist: httpx==0.28.1
Requires-Dist: python-dotenv==1.2.1
Provides-Extra: test
Requires-Dist: pytest-asyncio==1.2.0; extra == 'test'
Requires-Dist: pytest-mock==3.15.1; extra == 'test'
Requires-Dist: pytest==8.4.2; extra == 'test'
